MANIFEST.in
setup.py
doc/license.txt
doc/pySVG_Tutorial.doc
doc/html/.buildinfo
doc/html/gen.html
doc/html/genindex.html
doc/html/index.html
doc/html/modindex.html
doc/html/objects.inv
doc/html/py-modindex.html
doc/html/search.html
doc/html/searchindex.js
doc/html/_sources/gen.txt
doc/html/_sources/index.txt
doc/html/_static/ajax-loader.gif
doc/html/_static/basic.css
doc/html/_static/comment-bright.png
doc/html/_static/comment-close.png
doc/html/_static/comment.png
doc/html/_static/default.css
doc/html/_static/doctools.js
doc/html/_static/down-pressed.png
doc/html/_static/down.png
doc/html/_static/file.png
doc/html/_static/jquery.js
doc/html/_static/minus.png
doc/html/_static/plus.png
doc/html/_static/pygments.css
doc/html/_static/searchtools.js
doc/html/_static/sidebar.js
doc/html/_static/underscore.js
doc/html/_static/up-pressed.png
doc/html/_static/up.png
doc/html/_static/websupport.js
doc/html/generated/gen.html
doc/html/generated/pysvg.animate.html
doc/html/generated/pysvg.attributes.html
doc/html/generated/pysvg.builders.html
doc/html/generated/pysvg.core.html
doc/html/generated/pysvg.filter.html
doc/html/generated/pysvg.gradient.html
doc/html/generated/pysvg.linking.html
doc/html/generated/pysvg.parser.html
doc/html/generated/pysvg.script.html
doc/html/generated/pysvg.shape.html
doc/html/generated/pysvg.structure.html
doc/html/generated/pysvg.style.html
doc/html/generated/pysvg.text.html
doc/html/generated/pysvg.turtle.html
pysvg.egg-info/PKG-INFO
pysvg.egg-info/SOURCES.txt
pysvg.egg-info/dependency_links.txt
pysvg.egg-info/top_level.txt
src/pysvg/__init__.py
src/pysvg/animate.py
src/pysvg/attributes.py
src/pysvg/builders.py
src/pysvg/core.py
src/pysvg/filter.py
src/pysvg/gradient.py
src/pysvg/linking.py
src/pysvg/parser.py
src/pysvg/script.py
src/pysvg/shape.py
src/pysvg/structure.py
src/pysvg/style.py
src/pysvg/text.py
src/pysvg/turtle.py
src/pysvg/util.py